cleek/__init__.py
cleek/__main__.py
cleek/_parsers.py
cleek/_tasks.py
cleek/py.typed
cleek-0.1.0.dist-info/METADATA
cleek-0.1.0.dist-info/WHEEL
cleek-0.1.0.dist-info/entry_points.txt
cleek-0.1.0.dist-info/licenses/LICENSE
cleek-0.1.0.dist-info/RECORD
