Metadata-Version: 2.4
Name: cleek
Version: 0.1.0
Summary: A simple task runner that generates command line interfaces
Author-email: Peter Sutton <peter@foxdogstudio.com>
License-Expression: MIT
License-File: LICENSE
Classifier: Development Status :: 3 - Alpha
Classifier: Environment :: Console
Classifier: Framework :: Trio
Classifier: Intended Audience :: Developers
Classifier: License :: OSI Approved :: MIT License
Classifier: Natural Language :: English
Classifier: Operating System :: OS Independent
Classifier: Programming Language :: Python :: 3
Classifier: Topic :: Utilities
Requires-Python: >=3.13
Requires-Dist: rich
Requires-Dist: trio
